Workbook

Sheet 📊 Dashboard Summary
A1: 🚀 SmartShelf AI — 30-Day MVP Dashboard
A2: Portfolio Project | Next.js · NestJS · PostgreSQL · FastAPI · XGBoost | Target: 30 Days
A4: 📋 PROJECT METRICS | E4: 📆 WEEKLY PROGRESS | I4: ⏱ HOURS TRACKER
A5: 📌 Total Tasks | C5: =COUNTA('📅 30-Day Tracker'!A3:A34) -> 32 | E5: Week | F5: Done | G5: Total | I5: 📚 Planned Learn Hrs | L5: =SUMIF('📅 30-Day Tracker'!Q:Q,"<>",'📅 30-Day Tracker'!F:F) -> 0
A6: ✅ Completed Tasks | C6: =COUNTIF('📅 30-Day Tracker'!Q:Q,"Done") -> 0 | E6: Week 1 | F6: =COUNTIFS('📅 30-Day Tracker'!B:B,"Week 1",'📅 30-Day Tracker'!Q:Q,"Done") -> 0 | G6: =COUNTIF('📅 30-Day Tracker'!B:B,"Week 1") -> 9 | I6: 🔨 Planned Build Hrs | L6: =SUMIF('📅 30-Day Tracker'!Q:Q,"<>",'📅 30-Day Tracker'!H:H) -> 0
A7: 🔄 In Progress | C7: =COUNTIF('📅 30-Day Tracker'!Q:Q,"In Progress") -> 0 | E7: Week 2 | F7: =COUNTIFS('📅 30-Day Tracker'!B:B,"Week 2",'📅 30-Day Tracker'!Q:Q,"Done") -> 0 | G7: =COUNTIF('📅 30-Day Tracker'!B:B,"Week 2") -> 7 | I7: 📚 Actual Learn Hrs | L7: =SUM('⏱ Time Log'!C:C) -> 28
A8: ⏳ To Do | C8: =COUNTIF('📅 30-Day Tracker'!Q:Q,"To Do") -> 0 | E8: Week 3 | F8: =COUNTIFS('📅 30-Day Tracker'!B:B,"Week 3",'📅 30-Day Tracker'!Q:Q,"Done") -> 0 | G8: =COUNTIF('📅 30-Day Tracker'!B:B,"Week 3") -> 7 | I8: 🔨 Actual Build Hrs | L8: =SUM('⏱ Time Log'!D:D) -> 117.5
A9: 🚫 Blocked | C9: =COUNTIF('📅 30-Day Tracker'!Q:Q,"Blocked") -> 0 | E9: Week 4 | F9: =COUNTIFS('📅 30-Day Tracker'!B:B,"Week 4",'📅 30-Day Tracker'!Q:Q,"Done") -> 0 | G9: =COUNTIF('📅 30-Day Tracker'!B:B,"Week 4") -> 9 | I9: ⚙️ Debug/Commit Hrs | L9: =SUM('⏱ Time Log'!E:E) -> 13
A10: 📊 Completion % | C10: =IFERROR(C6/C5,0) -> 0 | I10: 🕐 Total Project Hrs | L10: =SUM('⏱ Time Log'!F:F) -> 158.5
A12: ℹ️ Charts auto-refresh when tracker data is updated. Use filters on '📅 30-Day Tracker' to drill down by module, priority, or week.

Sheet 📅 30-Day Tracker
A1: 📅 SmartShelf AI — Master 30-Day Task Tracker
A2: ID | B2: Week | C2: Day | D2: Module | E2: Learning Topic | F2: Learn Hrs | G2: Build Task | H2: Build Hrs | I2: Subtasks | J2: Deliverable | K2: Acceptance Criteria | L2: Dependency | M2: Testing Reqd | N2: Priority | O2: Risk Level | P2: Status | Q2: Blocker | R2: Notes
A3: 1 | B3: Week 1 | C3: 1 | D3: Setup & DevOps | E3: Project structure, Git repo, Docker Compose, env setup | F3: 1 | G3: Init Next.js + NestJS mono-repo, Prisma setup, Neon DB connection, GitHub repo | H3: 4 | I3: Create Next.js app, Create NestJS app, docker-compose.yml, .env files, Prisma init | J3: Mono-repo running locally; DB connection OK | K3: Repo accessible, npx prisma db pull works | L3: None | M3: No | N3: High | O3: Medium | P3: Done
A4: 2 | B4: Week 1 | C4: 1 | D4: Setup & DevOps | E4: Next.js App Router folder structure | F4: 0.5 | G4: Create base folder structure: /app, /components, /lib, /hooks | H4: 0.5 | I4: Create layout.tsx, globals.css, Tailwind config | J4: Tailwind + ShadCN rendering in browser | K4: npx shadcn@latest init runs clean | L4: Task 1 | M4: No | N4: High | O4: Low | P4: Done
A5: 3 | B5: Week 1 | C5: 2 | D5: Auth | E5: JWT, Guards, RBAC in NestJS | F5: 1.5 | G5: NestJS AuthModule: register, login, JWT strategy, roles guard | H5: 3.5 | I5: auth.module.ts, jwt.strategy.ts, roles.guard.ts, auth.controller.ts, register/login DTOs | J5: Register + Login APIs returning JWT | K5: POST /auth/register → 201, POST /auth/login → 200 + token | L5: Task 1 | M5: Yes | N5: High | O5: Medium | P5: Done
A6: 4 | B6: Week 1 | C6: 2 | D6: Auth | E6: Prisma User schema | F6: 0.5 | G6: User + Role tables in Prisma schema, run migration | H6: 0.5 | I6: schema.prisma: users table, run npx prisma migrate dev | J6: Users table in DB | K6: DB has users table, roles column | L6: Task 1 | M6: No | N6: High | O6: Low | P6: Done
A7: 5 | B7: Week 1 | C7: 3 | D7: Auth | E7: React Hook Form + Zod validation | F7: 1.5 | G7: Login + Register pages in Next.js with RHF + Zod, JWT stored in httpOnly cookie or localStorage | H7: 3.5 | I7: login/page.tsx, register/page.tsx, authSchema.ts, useAuth hook, API client | J7: Login flow working end-to-end | K7: User can register, login, token stored, protected route redirects | L7: Task 3 | M7: Yes | N7: High | O7: Medium | P7: Done
A8: 6 | B8: Week 1 | C8: 4 | D8: Auth | E8: Role-Based Access Control | F8: 1 | G8: Admin vs Staff role UI, protect routes and API endpoints | H8: 4 | I8: middleware.ts for route protection, RolesGuard on NestJS controllers, admin-only pages | J8: Admin sees all menus, Staff sees limited menus | K8: Admin can access /admin, Staff gets 403 on admin routes | L8: Task 3 | M8: Yes | N8: High | O8: Medium | P8: Done
A9: 7 | B9: Week 1 | C9: 5 | D9: Products | E9: Prisma schema — categories, products | F9: 1 | G9: NestJS CategoriesModule and ProductsModule: CRUD APIs | H9: 4 | I9: categories table, products table in schema.prisma, migrate, category CRUD endpoints | J9: GET/POST /categories, GET/POST/PUT/DELETE /products work | K9: All 4 CRUD operations return correct status codes | L9: Task 4 | M9: Yes | N9: High | O9: Medium | P9: Done
A10: 8 | B10: Week 1 | C10: 6 | D10: Products | E10: ShadCN table, forms, dialogs | F10: 1 | G10: Product list page, add/edit dialog with RHF+Zod, category filter | H10: 4 | I10: products/page.tsx, ProductTable, AddProductDialog, EditProductDialog | J10: Products list renders, add/edit/delete from UI works | K10: Product count updates on add, edit reflects in table | L10: Task 7 | M10: Yes | N10: High | O10: Low | P10: Done
A11: 9 | B11: Week 1 | C11: 7 | D11: Products | E11: Buffer/review day | F11: 0.5 | G11: Fix bugs, write unit tests for auth and products, review Week 1 | H11: 2.5 | I11: jest unit tests for AuthService, ProductsService | J11: Passing unit tests | K11: Jest reports 0 failures for auth + products | L11: Tasks 3-8 | M11: Yes | N11: Medium | O11: Low | P11: Done
A12: 10 | B12: Week 2 | C12: 8 | D12: Vendors | E12: Prisma vendors table, NestJS VendorsModule | F12: 1 | G12: Vendor CRUD APIs, vendor list + add/edit UI pages | H12: 4 | I12: vendors table, VendorsModule, VendorsController, VendorService | J12: GET/POST/PUT/DELETE /vendors work | K12: Vendor appears in list after add | L12: Task 1 | M12: Yes | N12: High | O12: Low | P12: Done
A13: 11 | B13: Week 2 | C13: 9 | D13: Purchases | E13: Purchase orders schema + API | F13: 1.5 | G13: NestJS PurchasesModule: create PO, auto-increment stock via stock_movements | H13: 3.5 | I13: purchase_orders, purchase_order_items, stock_movements tables; PurchasesController | J13: POST /purchases creates PO and increments product stock | K13: Stock quantity increases after purchase | L13: Task 10 | M13: Yes | N13: High | O13: High | P13: Done
A14: 12 | B14: Week 2 | C14: 10 | D14: Purchases | E14: Purchase entry UI | F14: 0.5 | G14: Purchase entry form: select vendor, add line items, submit | H14: 4.5 | I14: purchases/new/page.tsx, PurchaseForm, VendorSelect, LineItems component | J14: User can create a purchase bill from UI | K14: Stock quantity updates visible on product page | L14: Task 11 | M14: Yes | N14: High | O14: Medium | P14: In Progress
... A34: 32 | B34: Week 4 | C34: 30 | D34: Portfolio | E34: Final review + buffer | F34: 1 | G34: Final bug fixes, update portfolio site, LinkedIn post, submit to portfolio | H34: 4 | I34: All issues closed on GitHub, portfolio site updated | J34: All deployment URLs live and working | K34: Live URLs accessible; no critical bugs | L34: All | M34: No | N34: High | O34: Low | P34: To Do
A35: TOTAL | F35: =SUM(F3:F34) -> 31 | H35: =SUM(H3:H34) -> 114

Sheet 📆 Weekly Overview
A1: 📆 SmartShelf AI — Weekly Milestones & Hours Overview
A3: Week 1: Foundation + Auth + Products | Days 1–7 (Jul 1–7)
A4: Learn Hrs | B4: 6 | C4: Build Hrs | D4: 23 | E4: Total Hrs | F4: 29 | G4: Learn + Build / Day | H4: 4.1 | I4: Milestone | J4: Auth system + product management live
A5: KEY DELIVERABLES & MILESTONE CHECKLIST
A6: ✅ Mono-repo with Next.js + NestJS running locally
A7: ✅ Docker Compose + Neon PostgreSQL connection
A8: ✅ JWT register/login APIs with guards
A9: ✅ RBAC: Admin vs Staff roles working
A10: ✅ Product + Category CRUD (API + UI)
A11: ✅ Passing unit tests for auth and products
A13: Week 2: Inventory Core — Vendors, Purchases, Sales, Alerts | Days 8–14 (Jul 8–14)
A14: Learn Hrs | B14: 7 | C14: Build Hrs | D14: 26.5 | E14: Total Hrs | F14: 33.5 | G14: Learn + Build / Day | H14: 4.8 | I14: Milestone | J14: Full inventory in/out cycle working end-to-end
A15: KEY DELIVERABLES & MILESTONE CHECKLIST
A16: ✅ Vendor CRUD (API + UI)
A17: ✅ Purchase entry: creates PO + increments stock
A18: ✅ Sales billing: creates sale + decrements stock
A19: ✅ Low-stock alert banner
A20: ✅ Expiry alert with batch tracking
A21: ✅ Stock movement audit trail
A23: Week 3: Dashboard + Reports + ML Forecast Service | Days 15–21 (Jul 15–21)
A24: Learn Hrs | B24: 7 | C24: Build Hrs | D24: 25.5 | E24: Total Hrs | F24: 32.5 | G24: Learn + Build / Day | H24: 4.6 | I24: Milestone | J24: End-to-end data flow from DB → ML → UI
A25: KEY DELIVERABLES & MILESTONE CHECKLIST
A26: ✅ Dashboard cards (revenue, sales, low-stock count)
A27: ✅ Recharts: weekly sales trend + top products chart
A28: ✅ CSV report download
A29: ✅ FastAPI ML service running
A30: ✅ XGBoost model trained and saved
A31: ✅ Forecast API integrated in UI + rule-based fallback
A33: Week 4: Testing + Deployment + Portfolio Polish | Days 22–30 (Jul 22–30)
A34: Learn Hrs | B34: 6 | C34: Build Hrs | D34: 32.5 | E34: Total Hrs | F34: 38.5 | G34: Learn + Build / Day | H34: 5.5 | I34: Milestone | J34: Fully deployed, tested, portfolio-ready MVP
A35: KEY DELIVERABLES & MILESTONE CHECKLIST
A36: ✅ Jest unit tests (70%+ coverage on services)
A37: ✅ Supertest API integration tests
A38: ✅ Playwright E2E tests (8 scenarios)
A39: ✅ NestJS live on Render/Railway + Neon DB
A40: ✅ FastAPI ML service on Render Docker
A41: ✅ Next.js live on Vercel
A42: ✅ README + screenshots + demo video

Sheet 📚 Learning Plan
A1: 📚 SmartShelf AI — Structured Learning Plan
A2: Day | B2: Tech Topic | C2: Focus Area | D2: Resource / Official Docs | E2: Est. Hrs | F2: Completed? | G2: Notes
A3: 1 | B3: TypeScript Fundamentals | C3: Types, interfaces, generics, utility types | D3: https://www.typescriptlang.org/docs/ | E3: 1 | F3: Yes
A4: 1 | B4: Project Structure | C4: Next.js App Router, NestJS modular arch | D4: https://nextjs.org/docs/app | E4: 1 | F4: Yes
A5: 2 | B5: NestJS Core | C5: Modules, Controllers, Services, DI pattern | D5: https://docs.nestjs.com/ | E5: 1
A6: 2 | B6: JWT Authentication | C6: Access tokens, refresh tokens, guards | D6: https://docs.nestjs.com/security/authentication | E6: 0.5
A7: 3 | B7: React Hook Form | C7: useForm, Controller, FormProvider | D7: https://react-hook-form.com/docs | E7: 0.75
A8: 3 | B8: Zod Validation | C8: Schema definition, .parse, .safeParse | D8: https://zod.dev/ | E8: 0.75
A9: 4 | B9: RBAC Patterns | C9: Roles, Permissions, Guards in NestJS | D9: https://docs.nestjs.com/guards | E9: 1
A10: 5 | B10: Prisma ORM | C10: Schema, relations, migrations, queries | D10: https://www.prisma.io/docs | E10: 1
A11: 5 | B11: PostgreSQL Relations | C11: FK, joins, indexes, EXPLAIN ANALYZE | D11: https://www.postgresql.org/docs/ | E11: 0.5
A12: 6 | B12: ShadCN UI | C12: Components: Table, Dialog, Form, Badge | D12: https://ui.shadcn.com/docs | E12: 0.5
A13: 6 | B13: Tailwind CSS | C13: Responsive utilities, dark mode | D13: https://tailwindcss.com/docs | E13: 0.5
A14: 8 | B14: Prisma Relations | C14: One-to-many, many-to-many patterns | D14: https://www.prisma.io/docs/orm/prisma-schema/data-model/relations | E14: 0.5
A15: 9 | B15: Stock Movement Logic | C15: FIFO/FEFO batch deduction patterns | D15: https://docs.nestjs.com/techniques/database | E15: 1
A16: 10 | B16: NestJS Pipes | C16: ValidationPipe, custom pipes, DTOs | D16: https://docs.nestjs.com/pipes | E16: 0.5
... A30: 27 | B30: Vercel Deployment | C30: Project settings, env vars, preview URLs | D30: https://vercel.com/docs | E30: 0.5

Sheet 🛠 Tech Stack
A1: 🛠 SmartShelf AI — Tech Stack & Official Documentation
A2: Layer | B2: Technology | C2: Version | D2: Purpose | E2: Why Used in This Project | F2: Official Docs URL | G2: Notes
A3: Frontend | B3: Next.js | C3: 15 (App Router) | D3: React framework | E3: App Router for SSR/RSC, file-based routing, Vercel deployment | F3: https://nextjs.org/docs/app
A4: Frontend | B4: TypeScript | C4: 5.x | D4: Type safety | E4: Catch bugs at compile-time across FE+BE | F4: https://www.typescriptlang.org/docs/
A5: Frontend | B5: Tailwind CSS | C5: 3.x | D5: Utility CSS | E5: Rapid styling without custom CSS files | F5: https://tailwindcss.com/docs
A6: Frontend | B6: ShadCN UI | C6: latest | D6: Component library | E6: Accessible, copy-paste components built on Radix UI | F6: https://ui.shadcn.com/docs
A7: Frontend | B7: React Hook Form | C7: 7.x | D7: Form management | E7: Minimal re-renders, native HTML form integration | F7: https://react-hook-form.com/docs
A8: Frontend | B8: Zod | C8: 3.x | D8: Schema validation | E8: Runtime validation + TypeScript inference from one schema | F8: https://zod.dev/
A9: Frontend | B9: Recharts | C9: 2.x | D9: Data visualization | E9: React-native charts, composable, works with Tailwind | F9: https://recharts.org/en-US/api
A10: Backend | B10: NestJS | C10: 10.x | D10: Node.js framework | E10: Modular, DI, decorators — production-grade structure | F10: https://docs.nestjs.com/
A11: Backend | B11: TypeScript | C11: 5.x | D11: Type safety | E11: Same lang across FE+BE reduces context switching | F11: https://www.typescriptlang.org/docs/
A12: Backend | B12: JWT | C12: jsonwebtoken | D12: Authentication | E12: Stateless auth, scalable, industry standard | F12: https://docs.nestjs.com/security/authentication
A13: Backend | B13: Passport.js | C13: jwt strategy | D13: Auth middleware | E13: NestJS passport integration for JWT strategy | F13: http://www.passportjs.org/
A14: Database | B14: PostgreSQL | C14: 15.x | D14: Relational DB | E14: ACID transactions, strong relations for inventory | F14: https://www.postgresql.org/docs/
... A22: ML Service | B22: joblib | C22: latest | D22: Model persistence | E22: Efficient serialization of sklearn/xgboost models | F22: https://joblib.readthedocs.io/
A23: ML Data | B23: Online Retail Dataset | C23: UCI | D23: Training data | E23: Real retail transaction data for model training | F23: https://archive.ics.uci.edu/dataset/352/online+retail | G23: UCI ML Repository
A24: Testing | B24: Jest | C24: 29.x | D24: Unit testing | E24: NestJS default test runner, great mocking support | F24: https://jestjs.io/docs/getting-started
A25: Testing | B25: Supertest | C25: 6.x | D25: API testing | E25: HTTP assertions for NestJS E2E tests | F25: https://docs.nestjs.com/fundamentals/testing
A26: Testing | B26: Playwright | C26: latest | D26: E2E browser tests | E26: Cross-browser, auto-wait, great for UI flows | F26: https://playwright.dev/docs/intro
A27: DevOps | B27: Docker | C27: 24.x | D27: Containerization | E27: ML service containerized for consistent deployment | F27: https://docs.docker.com/get-started/
A28: DevOps | B28: Docker Compose | C28: 3.x | D28: Local multi-service | E28: Run all services locally with single command | F28: https://docs.docker.com/compose/
A29: Deployment | B29: Vercel | C29: cloud | D29: Frontend hosting | E29: Zero-config Next.js deploy, edge network | F29: https://vercel.com/docs
A30: Deployment | B30: Render/Railway | C30: cloud | D30: Backend hosting | E30: Easy Node.js + Docker deploys, free tier | F30: https://render.com/docs
A31: Deployment | B31: GitHub Actions | C31: optional | D31: CI/CD pipeline | E31: Automated test runs on push (optional for MVP) | F31: https://docs.github.com/en/actions | G31: Optional Week 4

Sheet 🗄 DB Schema
A1: 🗄 SmartShelf AI — PostgreSQL Database Schema Plan (Prisma)
A2: Table Name | B2: Purpose | C2: Important Fields | D2: Relations | E2: MVP Required | F2: Notes
A3: users | B3: Authentication & user management | C3: id (uuid), email, password_hash, role (ADMIN|STAFF), is_active, created_at | D3: shops via shop_members | E3: Yes | F3: Seed with 1 admin + 1 staff user
A4: shops | B4: Shop/store profile | C4: id, name, address, phone, currency, timezone, owner_id | D4: owner → users; shop_members | E4: Yes | F4: Single shop for MVP
A5: shop_members | B5: Many-to-many: user ↔ shop | C5: id, user_id, shop_id, role, created_at | D5: users, shops | E5: Yes | F5: Enables multi-shop future
A6: categories | B6: Product categories | C6: id, name, description, shop_id, created_at | D6: products | E6: Yes
A7: products | B7: Product catalog | C7: id, name, sku, barcode, category_id, unit, reorder_level, selling_price, shop_id, created_at | D7: categories, product_batches, sale_items, purchase_order_items | E7: Yes | F7: reorder_level triggers low-stock alert
A8: product_batches | B8: Batch/lot tracking for expiry | C8: id, product_id, batch_no, expiry_date, quantity_remaining, purchase_order_item_id, created_at | D8: products, purchase_order_items | E8: Yes | F8: Enables FEFO deduction + expiry alerts
A9: vendors | B9: Supplier/vendor management | C9: id, name, contact_person, phone, email, address, shop_id, created_at | D9: purchase_orders | E9: Yes
A10: purchase_orders | B10: Purchase (inbound stock) header | C10: id, vendor_id, shop_id, po_date, total_amount, status, created_by, created_at | D10: purchase_order_items, vendors | E10: Yes | F10: status: PENDING|RECEIVED|CANCELLED
A11: purchase_order_items | B11: Line items of a purchase order | C11: id, purchase_order_id, product_id, quantity, unit_price, expiry_date, batch_no | D11: purchase_orders, products, product_batches | E11: Yes | F11: Creates product_batch on receive
A12: sales | B12: Sale (outbound) bill header | C12: id, shop_id, sale_date, total_amount, discount, customer_name, created_by, created_at | D12: sale_items | E12: Yes
A13: sale_items | B13: Line items of a sale | C13: id, sale_id, product_id, quantity, unit_price, total_price | D13: sales, products | E13: Yes | F13: Triggers stock_movements on create
A14: stock_movements | B14: Audit log for all stock changes | C14: id, product_id, movement_type (IN|OUT|ADJUSTMENT), quantity, reference_id, reference_type, batch_id, created_by, created_at | D14: products, users | E14: Yes | F14: Immutable audit trail
A15: forecast_results | B15: ML demand forecast storage | C15: id, product_id, forecast_date, predicted_quantity, model_version, confidence, created_at | D15: products | E15: Yes | F15: Cached from ML service call
A16: reports | B16: Metadata for generated CSV reports | C16: id, shop_id, report_type, date_range_start, date_range_end, file_url, created_by, created_at | D16: shops, users | E16: Yes | F16: Store S3/local URL of generated CSV

Sheet 🔌 API Reference
A1: 🔌 SmartShelf AI — REST API Reference
A2: Module | B2: Method | C2: Endpoint | D2: Description | E2: Auth Reqd | F2: Role Reqd | G2: Request Body (key fields) | H2: Response | I2: Status
A3: Auth | B3: POST | C3: /auth/register | D3: Register new user | E3: No | F3: — | G3: { email, password, name, role } | H3: { id, email, role, token } | I3: 201
A4: Auth | B4: POST | C4: /auth/login | D4: Login and get JWT | E4: No | F4: — | G4: { email, password } | H4: { access_token, user } | I4: 200
A5: Auth | B5: GET | C5: /auth/me | D5: Get current user profile | E5: Yes | F5: Any | G5: — | H5: { id, email, name, role } | I5: 200
A6: Auth | B6: POST | C6: /auth/refresh | D6: Refresh access token | E6: Yes | F6: Any | G6: { refresh_token } | H6: { access_token } | I6: 200
A7: Shops | B7: GET | C7: /shops/:id | D7: Get shop profile | E7: Yes | F7: Any | G7: — | H7: { id, name, address, currency } | I7: 200
A8: Shops | B8: PUT | C8: /shops/:id | D8: Update shop profile | E8: Yes | F8: Admin | G8: { name, address, phone, currency } | H8: Updated shop object | I8: 200
A9: Shops | B9: POST | C9: /shops/:id/members | D9: Add member to shop | E9: Yes | F9: Admin | G9: { user_id, role } | H9: { shop_member } | I9: 201
A10: Categories | B10: GET | C10: /categories | D10: List all categories | E10: Yes | F10: Any | G10: — | H10: [{ id, name }] | I10: 200
A11: Categories | B11: POST | C11: /categories | D11: Create category | E11: Yes | F11: Admin | G11: { name, description } | H11: { id, name } | I11: 201
A12: Categories | B12: PUT | C12: /categories/:id | D12: Update category | E12: Yes | F12: Admin | G12: { name, description } | H12: Updated category | I12: 200
A13: Categories | B13: DELETE | C13: /categories/:id | D13: Delete category | E13: Yes | F13: Admin | G13: — | H13: { message } | I13: 200
... A39: ML Forecast | B39: GET | C39: /forecast/results/:product_id | D39: Get cached forecast | E39: Yes | F39: Any | G39: — | H39: [{ forecast_date, predicted_qty }] | I39: 200

Sheet 🧪 Testing Checklist
A1: 🧪 SmartShelf AI — Testing Checklist
A2: # | B2: Test Type | C2: Test Case | D2: Module | E2: Expected Result | F2: Pass/Fail | G2: Day Tested | H2: Notes
A3: 1 | B3: Unit | C3: AuthService.register() creates user with hashed password | D3: Auth | E3: User saved with bcrypt hash, not plain text | F3: Pending | G3: 22
A4: 2 | B4: Unit | C4: AuthService.login() returns JWT on valid credentials | D4: Auth | E4: Returns { access_token } string | F4: Pending | G4: 22
A5: 3 | B5: Unit | C5: AuthService.login() throws 401 on wrong password | D5: Auth | E5: UnauthorizedException thrown | F5: Pending | G5: 22
A6: 4 | B6: Unit | C6: ProductsService.create() creates product record | D6: Products | E6: Product with correct fields saved to DB | F6: Pending | G6: 22
A7: 5 | B7: Unit | C7: ProductsService.findAll() returns paginated list | D7: Products | E7: Array with pagination metadata | F7: Pending | G7: 22
A8: 6 | B8: Unit | C8: SalesService.create() decrements stock quantity | D8: Sales | E8: product quantity decreases by sale quantity | F8: Pending | G8: 22
A9: 7 | B9: Unit | C9: SalesService.create() throws 400 if insufficient stock | D9: Sales | E9: BadRequestException: Insufficient stock | F9: Pending | G9: 22
A10: 8 | B10: Unit | C10: PurchasesService.create() increments stock quantity | D10: Purchases | E10: product quantity increases by purchase quantity | F10: Pending | G10: 22
A11: 9 | B11: Unit | C11: AlertsService returns low-stock products | D11: Inventory | E11: Products below reorder_level in result | F11: Pending | G11: 22
A12: 10 | B12: Unit | C12: AlertsService returns expiring products (< 7 days) | D12: Inventory | E12: Batches with expiry_date < today+7 returned | F12: Pending | G12: 22
A13: 11 | B13: Unit | C13: ForecastService falls back to rule-based if ML down | D13: ML Forecast | E13: Returns rolling average, no crash | F13: Pending | G13: 22
A14: 12 | B14: API | C14: POST /auth/register → 201 with valid payload | D14: Auth | E14: { id, email, role } in response | F14: Pending | G14: 23
... A38: 36 | B38: E2E | C38: Staff cannot access admin-only pages | D38: Auth/RBAC | E38: Redirect to /unauthorized or 403 page | F38: Pending | G38: 24

Sheet 🚀 Deployment
A1: 🚀 SmartShelf AI — Deployment Checklist
A2: # | B2: Service | C2: Task | D2: Platform | E2: Status | F2: Notes | G2: Target Day
A3: 1 | B3: Database | C3: Create Neon PostgreSQL project | D3: Neon | E3: To Do | F3: Free tier, copy connection string | G3: Day 1
A4: 2 | B4: Database | C4: Set DATABASE_URL in .env | D4: Local | E4: To Do | F4: postgres://user:pass@host/db | G4: Day 1
A5: 3 | B5: Database | C5: Run prisma migrate deploy in production | D5: Neon | E5: To Do | F5: npx prisma migrate deploy | G5: Day 25
A6: 4 | B6: Database | C6: Seed production DB with demo data | D6: Neon | E6: To Do | F6: npx prisma db seed | G6: Day 25
A7: 5 | B7: Backend | C7: Create Render/Railway service | D7: Render | E7: To Do | F7: Node.js service, connect to GitHub repo | G7: Day 25
A8: 6 | B8: Backend | C8: Set all env vars on Render | D8: Render | E8: To Do | F8: DATABASE_URL, JWT_SECRET, ML_SERVICE_URL, CORS_ORIGIN | G8: Day 25
A9: 7 | B9: Backend | C9: Deploy NestJS and verify /health endpoint | D9: Render | E9: To Do | F9: GET /health → 200 OK | G9: Day 25
A10: 8 | B10: Backend | C10: Enable CORS for Vercel frontend URL | D10: NestJS | E10: To Do | F10: app.enableCors({ origin: process.env.CORS_ORIGIN }) | G10: Day 25
A11: 9 | B11: Backend | C11: Verify all API endpoints on production URL | D11: Render | E11: To Do | F11: Use Postman/Insomnia with production base URL | G11: Day 25
A12: 10 | B12: ML Service | C12: Create Dockerfile for FastAPI app | D12: Local | E12: To Do | F12: FROM python:3.11-slim, pip install -r requirements.txt | G12: Day 26
A13: 11 | B13: ML Service | C13: Test Docker build locally | D13: Local | E13: To Do | F13: docker build -t smartshelf-ml . | G13: Day 26
A14: 12 | B14: ML Service | C14: Create Render Docker service | D14: Render | E14: To Do | F14: New service → Docker, connect to GitHub | G14: Day 26
... A29: 27 | B29: Final | C29: Share on LinkedIn / portfolio site | D29: LinkedIn | E29: To Do | F29: Post with live URL, tech stack, screenshots | G29: Day 30

Sheet ⏱ Time Log
A1: ⏱ SmartShelf AI — Daily Time Log
A2: Day | B2: Date | C2: Learn Hrs | D2: Build Hrs | E2: Debug/Commit Hrs | F2: Total Hrs | G2: Main Task Done | H2: Blockers | I2: Notes
A3: 1 | B3: Day 1 | C3: 1 | D3: 3 | E3: 0.5 | F3: =IFERROR(C3+D3+E3,0) -> 4.5
A4: 2 | B4: Day 2 | F4: =IFERROR(C4+D4+E4,0) -> 0
A5: 3 | B5: Day 3 | F5: =IFERROR(C5+D5+E5,0) -> 0
A6: 4 | B6: Day 4 | F6: =IFERROR(C6+D6+E6,0) -> 0
A7: 5 | B7: Day 5 | F7: =IFERROR(C7+D7+E7,0) -> 0
A8: 6 | B8: Day 6 | F8: =IFERROR(C8+D8+E8,0) -> 0
A9: 7 | B9: Day 7 | F9: =IFERROR(C9+D9+E9,0) -> 0
A10: 8 | B10: Day 8 | F10: =IFERROR(C10+D10+E10,0) -> 0
A11: 9 | B11: Day 9 | F11: =IFERROR(C11+D11+E11,0) -> 0
A12: 10 | B12: Day 10 | F12: =IFERROR(C12+D12+E12,0) -> 0
A13: 11 | B13: Day 11 | F13: =IFERROR(C13+D13+E13,0) -> 0
A14: 12 | B14: Day 12 | F14: =IFERROR(C14+D14+E14,0) -> 0
A15: 13 | B15: Day 13 | F15: =IFERROR(C15+D15+E15,0) -> 0
... A32: 30 | B32: Day 30 | F32: =IFERROR(C32+D32+E32,0) -> 0
A33: TOTAL | B33: 30 Days | C33: =SUM(C3:C32) -> 1 | D33: =SUM(D3:D32) -> 3 | E33: =SUM(E3:E32) -> 0.5 | F33: =SUM(F3:F32) -> 4.5 | G33: Fill in daily to track progress
A34: TARGET | C34: 26 | D34: 111.5 | E34: 12 | F34: 149.5 | G34: ~5-6 hrs/day for 30 days

Sheet ⚠️ Risk & Fallback
A1: ⚠️ SmartShelf AI — Risk Register & Fallback Plan
A2: # | B2: Risk Category | C2: Risk Description | D2: Probability | E2: Impact | F2: Fallback Plan | G2: Owner/Day
A3: 1 | B3: ML/Data | C3: XGBoost model training takes too long or fails to converge | D3: Medium | E3: High | F3: Use rule-based fallback: 7-day rolling average of stock movements for each product. Ship fallback first, ML second. | G3: Day 23 / Self
A4: 2 | B4: ML/Data | C4: Online Retail dataset preprocessing is complex | D4: Medium | E4: Medium | F4: Use synthetic data: generate 6-month sales history per product using Python random. Train on that to prove pipeline works. | G4: Day 18 / Self
A5: 3 | B5: ML/Data | C5: FastAPI ML service has cold start issues on Render free tier | D5: High | E5: Medium | F5: Add /health ping from NestJS on startup. Show 'forecast loading' state in UI. Cache last forecast in DB. | G5: Day 26 / Self
A6: 4 | B6: Backend | C6: Prisma schema becomes too complex with all tables | D6: Medium | E6: High | F6: Start with: users, products, purchases, sales, stock_movements only. Add vendors, batches, forecasts incrementally. | G6: Day 4 / Self
A7: 5 | B7: Backend | C7: NestJS circular dependencies between modules | D7: Medium | E7: Medium | F7: Use forwardRef() sparingly. Keep modules loosely coupled. StockMovements should be a separate service injected into Sales/Purchases. | G7: Day 11 / Self
A8: 6 | B8: Backend | C8: Stock deduction logic has edge cases (partial batches) | D8: High | E8: High | F8: Implement simple total-quantity deduction first (no FEFO). Add FEFO batch logic only after basic sale billing works. | G8: Day 13 / Self
A9: 7 | B9: Frontend | C9: UI takes too long to build with custom designs | D9: High | E9: Medium | F9: Use only ShadCN pre-built components (Table, Dialog, Card, Badge). Zero custom CSS. Tailwind utilities only. | G9: Day 6 / Self
A10: 8 | B10: Frontend | C10: React Hook Form + Zod integration issues | D10: Low | E10: Medium | F10: Use RHF v7 zodResolver. Copy patterns from official RHF docs. Test each form in isolation before integration. | G10: Day 3 / Self
A11: 9 | B11: Deployment | C11: Backend deployment fails due to env var mismatch | D11: Medium | E11: High | F11: Keep a .env.production file template in repo (no secrets). Test deployment script locally with Docker before pushing. | G11: Day 25 / Self
A12: 10 | B12: Deployment | C12: Render/Railway free tier sleeps after inactivity | D12: High | E12: Medium | F12: Use Render cron job or external uptime monitor (cron-job.org) to ping /health every 14 minutes. | G12: Day 27 / Self
A13: 11 | B13: Deployment | C13: Vercel build fails due to TypeScript errors | D13: Medium | E13: Medium | F13: Run npm run build locally before pushing. Fix all TS errors. Set strictNullChecks: true from Day 1. | G13: Day 27 / Self
A14: 12 | B14: Time | C14: Week 3 ML + Dashboard takes longer than planned | D14: High | E14: Medium | F14: Cut advanced charts (keep only 1 line + 1 bar). Ship basic forecast as text-only table first, add chart later. | G14: Day 21 / Self
... A17: 15 | B17: Security | C17: JWT secret leaked to GitHub | D17: Low | E17: Critical | F17: Use .env files, never commit secrets. Add .env to .gitignore on Day 1. Use GitHub Secrets for CI/CD. | G17: Day 1 / Self

Sheet 🔮 Deferred Features
A1: 🔮 SmartShelf AI — Post-MVP Deferred Features
A2: # | B2: Feature | C2: Category | D2: Complexity | E2: Business Value | F2: Tech Stack Hint | G2: Target Phase
A3: 1 | B3: Customer segmentation (RFM analysis) | C3: ML | D3: High | E3: High | F3: Pandas + KMeans/DBSCAN, new /segments endpoint in FastAPI | G3: v1.1 - Post MVP
A4: 2 | B4: Association rule mining (Market basket) | C4: ML | D4: High | E4: Medium | F4: mlxtend FP-Growth, recommend complementary products | G4: v1.1 - Post MVP
A5: 3 | B5: Anomaly detection for sales/inventory | C5: ML | D5: High | E5: High | F5: Isolation Forest or Z-score on daily sales time series | G5: v1.2
A6: 4 | B6: Payment gateway integration | C6: Payments | D6: High | E6: High | F6: Razorpay or Stripe SDK, webhook for payment confirmation | G6: v1.1 - Post MVP
A7: 5 | B7: GST / tax filing export | C7: Compliance | D7: Medium | E7: High | F7: GST GSTR-1 format CSV/JSON, Indian tax calculation | G7: v2.0
A8: 6 | B8: Advanced PDF reports (with charts) | C8: Reports | D8: Medium | E8: Medium | F8: WeasyPrint or Puppeteer PDF generation | G8: v1.1 - Post MVP
A9: 7 | B9: WhatsApp / SMS low-stock alerts | C9: Notifications | D9: Medium | E9: High | F9: Twilio SMS or WhatsApp Business API | G9: v1.1 - Post MVP
A10: 8 | B10: Email notifications (SMTP) | C10: Notifications | D10: Low | E10: Medium | F10: Nodemailer in NestJS, daily digest email | G10: v1.1 - Post MVP
A11: 9 | B11: Mobile app (React Native / Flutter) | C11: Mobile | D11: Very High | E11: High | F11: Expo React Native or Flutter, same NestJS backend | G11: v2.0
A12: 10 | B12: Progressive Web App (PWA) | C12: Frontend | D12: Low | E12: Medium | F12: next-pwa, service worker, offline mode | G12: v1.1 - Post MVP
A13: 11 | B13: Multi-location / multi-branch support | C13: Architecture | D13: High | E13: High | F13: shop_locations table, location-based stock queries | G13: v2.0
A14: 12 | B14: SaaS billing (subscription tiers) | C14: Business | D14: Very High | E14: High | F14: Stripe Billing, plan-based feature gating | G14: v2.0
... A24: 22 | B24: Data export to Google Sheets | C24: Integration | D24: Medium | E24: Medium | F24: Google Sheets API v4, scheduled sync | G24: v2.0
